src/__init__.py
src/engine.py
tests/__init__.py
tests/test_engine.py
tiny_fnc_engine/__init__.py
tiny_fnc_engine/engine.py
tiny_fnc_engine-0.2.1.dist-info/LICENSE
tiny_fnc_engine-0.2.1.dist-info/METADATA
tiny_fnc_engine-0.2.1.dist-info/WHEEL
tiny_fnc_engine-0.2.1.dist-info/top_level.txt
tiny_fnc_engine-0.2.1.dist-info/RECORD
