Metadata-Version: 2.1
Name: tiny_fnc_engine
Version: 0.2.1
Summary: Extremely lightweight and minimal function calling engine
Home-page: https://github.com/AtakanTekparmak/tiny_fnc_engine
Author: Atakan Tekparmak
Author-email: atakantekerparmak@gmail.com
License-File: LICENSE
Requires-Dist: pydantic ==2.8.2
